MicroLIA_Sim/__init__.py
MicroLIA_Sim/microlensing.py
MicroLIA_Sim/param_generation.py
MicroLIA_Sim/variable_stars.py
MicroLIA_Sim/data/__init__.py
MicroLIA_Sim/data/mt_boson_list.csv
MicroLIA_Sim/data/mt_nfw_list.csv
microlia_simulate-0.1.0.dist-info/licenses/LICENSE
microlia_simulate-0.1.0.dist-info/METADATA
microlia_simulate-0.1.0.dist-info/WHEEL
microlia_simulate-0.1.0.dist-info/top_level.txt
microlia_simulate-0.1.0.dist-info/RECORD
