Metadata-Version: 2.4
Name: MicroLIA-Simulate
Version: 0.1.0
Summary: A standalone simulation engine for the MicroLIA framework, designed as a lightweight sister package for generating synthetic astronomical datasets.
Home-page: https://github.com/Professor-G/MicroLIA-Simulate
Author: Daniel Godines
Author-email: dan@gmail.com
License: GPL-3.0
Classifier: Development Status :: 4 - Beta
Classifier: Intended Audience :: Science/Research
Classifier: Topic :: Scientific/Engineering :: Astronomy
Classifier: Topic :: Scientific/Engineering :: Physics
Classifier: License :: OSI Approved :: GNU General Public License v3 (GPLv3)
Classifier: Programming Language :: Python :: 3
Classifier: Programming Language :: Python :: 3.12
Requires-Python: >=3.12
License-File: LICENSE
Requires-Dist: numpy
Requires-Dist: pandas
Requires-Dist: scipy
Requires-Dist: astropy
Requires-Dist: matplotlib
Requires-Dist: pyLIMA==1.9.8
Requires-Dist: astro-datalab>=2.22.1
Dynamic: author
Dynamic: author-email
Dynamic: classifier
Dynamic: home-page
Dynamic: license
Dynamic: license-file
Dynamic: requires-dist
Dynamic: requires-python
Dynamic: summary
